LICENSE.rst
LICENSE_GPL.rst
MANIFEST.in
README.rst
bootstrap.py
buildout.cfg
dev.cfg
setup.py
test.sh
etc/base.cfg
src/agx/__init__.py
src/agx.dev.egg-info/PKG-INFO
src/agx.dev.egg-info/SOURCES.txt
src/agx.dev.egg-info/dependency_links.txt
src/agx.dev.egg-info/entry_points.txt
src/agx.dev.egg-info/namespace_packages.txt
src/agx.dev.egg-info/not-zip-safe
src/agx.dev.egg-info/requires.txt
src/agx.dev.egg-info/top_level.txt
src/agx/dev/__init__.py
src/agx/dev/main.py