Metadata-Version: 1.1
Name: agx.dev
Version: 1.0a1
Summary: AGX development bundle
Home-page: https://github.com/bluedynamics/agx.dev
Author: BlueDynamics Alliance
Author-email: dev@bluedynamics.com
License: GNU General Public Licence
Keywords: AGX,Code Generator
Platform: UNKNOWN
Classifier: Development Status :: 3 - Alpha
Classifier: License :: OSI Approved :: GNU General Public License (GPL)
Classifier: Programming Language :: Python
